{"configuration": "2dt - Centralities - DiGraph", "dtime": "20240822-024020", "multi_class": false, "learning_rate": 0.001, "dataset_name": "cic_ton_iot", "num_classes": 2, "labels_names": {"0": "benign", "1": "attack"}, "input_dim": 44, "scores": {"server": {"0": {"accuracy": 0.5618412067656138, "recall": 0.5618412067656138, "precision": 0.6292293424566973, "f1s": 0.5038884865874059, "FPR": 0.7763505286632999, "FNR": 0.08838344498104585, "class_report": "              precision    recall  f1-score   support\n\n           0       0.72      0.22      0.34    238999\n           1       0.53      0.91      0.67    231084\n\n    accuracy                           0.56    470083\n   macro avg       0.63      0.57      0.51    470083\nweighted avg       0.63      0.56      0.50    470083\n"}, "1": {"accuracy": 0.6179695926038593, "recall": 0.6179695926038593, "precision": 0.6572658477684903, "f1s": 0.5960590426737953, "FPR": 0.6136092619634391, "FNR": 0.1425196032611518, "class_report": "              precision    recall  f1-score   support\n\n           0       0.74      0.39      0.51    238999\n           1       0.57      0.86      0.69    231084\n\n    accuracy                           0.62    470083\n   macro avg       0.66      0.62      0.60    470083\nweighted avg       0.66      0.62      0.60    470083\n"}, "2": {"accuracy": 0.6923585834841932, "recall": 0.6923585834841932, "precision": 0.8083129654217289, "f1s": 0.658039167666551, "FPR": 1.6736471700718413e-05, "FNR": 0.6258027383981583, "class_report": "              precision    recall  f1-score   support\n\n           0       0.62      1.00      0.77    238999\n           1       1.00      0.37      0.54    231084\n\n    accuracy                           0.69    470083\n   macro avg       0.81      0.69      0.66    470083\nweighted avg       0.81      0.69      0.66    470083\n"}, "3": {"accuracy": 0.6745127988036155, "recall": 0.6745127988036155, "precision": 0.7605801377162333, "f1s": 0.6477414763064027, "FPR": 0.6002284528387148, "FNR": 0.04133561821675235, "class_report": "              precision    recall  f1-score   support\n\n           0       0.91      0.40      0.56    238999\n           1       0.61      0.96      0.74    231084\n\n    accuracy                           0.67    470083\n   macro avg       0.76      0.68      0.65    470083\nweighted avg       0.76      0.67      0.65    470083\n"}, "4": {"accuracy": 0.7040905542212759, "recall": 0.7040905542212759, "precision": 0.8126537153340577, "f1s": 0.6780648012503911, "FPR": 0.5796802497081578, "FNR": 0.002419033771269322, "class_report": "              precision    recall  f1-score   support\n\n           0       0.99      0.42      0.59    238999\n           1       0.62      1.00      0.77    231084\n\n    accuracy                           0.70    470083\n   macro avg       0.81      0.71      0.68    470083\nweighted avg       0.81      0.70      0.68    470083\n"}, "5": {"accuracy": 0.7143738446189289, "recall": 0.7143738446189289, "precision": 0.8097392787169201, "f1s": 0.6924524220234962, "FPR": 0.5524374578973134, "FNR": 0.009676135085077288, "class_report": "              precision    recall  f1-score   support\n\n           0       0.98      0.45      0.61    238999\n           1       0.63      0.99      0.77    231084\n\n    accuracy                           0.71    470083\n   macro avg       0.81      0.72      0.69    470083\nweighted avg       0.81      0.71      0.69    470083\n"}, "6": {"accuracy": 0.9635170810261167, "recall": 0.9635170810261167, "precision": 0.9659493237399391, "f1s": 0.9634461610724007, "FPR": 7.531412265323286e-05, "FNR": 0.07413754305793564, "class_report": "              precision    recall  f1-score   support\n\n           0       0.93      1.00      0.97    238999\n           1       1.00      0.93      0.96    231084\n\n    accuracy                           0.96    470083\n   macro avg       0.97      0.96      0.96    470083\nweighted avg       0.97      0.96      0.96    470083\n"}, "7": {"accuracy": 0.9613047057647267, "recall": 0.9613047057647267, "precision": 0.9640304749618916, "f1s": 0.9612215785084466, "FPR": 7.531412265323286e-05, "FNR": 0.07863807100448322, "class_report": "              precision    recall  f1-score   support\n\n           0       0.93      1.00      0.96    238999\n           1       1.00      0.92      0.96    231084\n\n    accuracy                           0.96    470083\n   macro avg       0.96      0.96      0.96    470083\nweighted avg       0.96      0.96      0.96    470083\n"}, "8": {"accuracy": 0.8149582095076827, "recall": 0.8149582095076827, "precision": 0.8426080022074838, "f1s": 0.8116964387258963, "FPR": 0.32008920539416486, "FNR": 0.04536878364577383, "class_report": "              precision    recall  f1-score   support\n\n           0       0.94      0.68      0.79    238999\n           1       0.74      0.95      0.84    231084\n\n    accuracy                           0.81    470083\n   macro avg       0.84      0.82      0.81    470083\nweighted avg       0.84      0.81      0.81    470083\n"}, "9": {"accuracy": 0.9544208150475554, "recall": 0.9544208150475554, "precision": 0.9581600638102191, "f1s": 0.9542909559258711, "FPR": 6.276176887769405e-05, "FNR": 0.09265461909954821, "class_report": "              precision    recall  f1-score   support\n\n           0       0.92      1.00      0.96    238999\n           1       1.00      0.91      0.95    231084\n\n    accuracy                           0.95    470083\n   macro avg       0.96      0.95      0.95    470083\nweighted avg       0.96      0.95      0.95    470083\n"}, "10": {"accuracy": 0.9479623811114207, "recall": 0.9479623811114207, "precision": 0.9527883518238387, "f1s": 0.94777517339637, "FPR": 2.9288825476257222e-05, "FNR": 0.10582731820463555, "class_report": "              precision    recall  f1-score   support\n\n           0       0.91      1.00      0.95    238999\n           1       1.00      0.89      0.94    231084\n\n    accuracy                           0.95    470083\n   macro avg       0.95      0.95      0.95    470083\nweighted avg       0.95      0.95      0.95    470083\n"}, "11": {"accuracy": 0.9841049346604749, "recall": 0.9841049346604749, "precision": 0.9845829067929539, "f1s": 0.9840967051685835, "FPR": 6.276176887769405e-05, "FNR": 0.03226965086288969, "class_report": "              precision    recall  f1-score   support\n\n           0       0.97      1.00      0.98    238999\n           1       1.00      0.97      0.98    231084\n\n    accuracy                           0.98    470083\n   macro avg       0.98      0.98      0.98    470083\nweighted avg       0.98      0.98      0.98    470083\n"}, "12": {"accuracy": 0.946277572258516, "recall": 0.946277572258516, "precision": 0.9514033737199815, "f1s": 0.9460731971171025, "FPR": 4.184117925179603e-05, "FNR": 0.10924166104100673, "class_report": "              precision    recall  f1-score   support\n\n           0       0.90      1.00      0.95    238999\n           1       1.00      0.89      0.94    231084\n\n    accuracy                           0.95    470083\n   macro avg       0.95      0.95      0.95    470083\nweighted avg       0.95      0.95      0.95    470083\n"}, "13": {"accuracy": 0.9575372859686481, "recall": 0.9575372859686481, "precision": 0.9608010295610682, "f1s": 0.9574302444777203, "FPR": 5.8577650952514444e-05, "FNR": 0.08631926052863893, "class_report": "              precision    recall  f1-score   support\n\n           0       0.92      1.00      0.96    238999\n           1       1.00      0.91      0.95    231084\n\n    accuracy                           0.96    470083\n   macro avg       0.96      0.96      0.96    470083\nweighted avg       0.96      0.96      0.96    470083\n"}, "14": {"accuracy": 0.9778741201021948, "recall": 0.9778741201021948, "precision": 0.9785167760481891, "f1s": 0.977859631122121, "FPR": 0.0035606843543278424, "FNR": 0.04132696335531668, "class_report": "              precision    recall  f1-score   support\n\n           0       0.96      1.00      0.98    238999\n           1       1.00      0.96      0.98    231084\n\n    accuracy                           0.98    470083\n   macro avg       0.98      0.98      0.98    470083\nweighted avg       0.98      0.98      0.98    470083\n"}, "15": {"accuracy": 0.959992171595229, "recall": 0.959992171595229, "precision": 0.9629082258092362, "f1s": 0.9599009548946079, "FPR": 1.6736471700718413e-05, "FNR": 0.0813686797874366, "class_report": "              precision    recall  f1-score   support\n\n           0       0.93      1.00      0.96    238999\n           1       1.00      0.92      0.96    231084\n\n    accuracy                           0.96    470083\n   macro avg       0.96      0.96      0.96    470083\nweighted avg       0.96      0.96      0.96    470083\n"}, "16": {"accuracy": 0.9459648615244541, "recall": 0.9459648615244541, "precision": 0.9511560360797391, "f1s": 0.9457568833458788, "FPR": 0.0, "FNR": 0.1099210676637067, "class_report": "              precision    recall  f1-score   support\n\n           0       0.90      1.00      0.95    238999\n           1       1.00      0.89      0.94    231084\n\n    accuracy                           0.95    470083\n   macro avg       0.95      0.95      0.95    470083\nweighted avg       0.95      0.95      0.95    470083\n"}, "17": {"accuracy": 0.945962734240549, "recall": 0.945962734240549, "precision": 0.9511542979064261, "f1s": 0.9457547333799419, "FPR": 0.0, "FNR": 0.10992539509442453, "class_report": "              precision    recall  f1-score   support\n\n           0       0.90      1.00      0.95    238999\n           1       1.00      0.89      0.94    231084\n\n    accuracy                           0.95    470083\n   macro avg       0.95      0.95      0.95    470083\nweighted avg       0.95      0.95      0.95    470083\n"}, "18": {"accuracy": 0.9537507206174228, "recall": 0.9537507206174228, "precision": 0.9575976747070674, "f1s": 0.953615520759451, "FPR": 5.439353302733484e-05, "FNR": 0.09402641463710167, "class_report": "              precision    recall  f1-score   support\n\n           0       0.92      1.00      0.96    238999\n           1       1.00      0.91      0.95    231084\n\n    accuracy                           0.95    470083\n   macro avg       0.96      0.95      0.95    470083\nweighted avg       0.96      0.95      0.95    470083\n"}, "19": {"accuracy": 0.948419747151035, "recall": 0.948419747151035, "precision": 0.9531594802801944, "f1s": 0.9482372359534533, "FPR": 5.8577650952514444e-05, "FNR": 0.10486662858527634, "class_report": "              precision    recall  f1-score   support\n\n           0       0.91      1.00      0.95    238999\n           1       1.00      0.90      0.94    231084\n\n    accuracy                           0.95    470083\n   macro avg       0.95      0.95      0.95    470083\nweighted avg       0.95      0.95      0.95    470083\n"}, "20": {"accuracy": 0.9605473926944816, "recall": 0.9605473926944816, "precision": 0.9633884032172569, "f1s": 0.9604594982543619, "FPR": 0.0, "FNR": 0.08025653009295321, "class_report": "              precision    recall  f1-score   support\n\n           0       0.93      1.00      0.96    238999\n           1       1.00      0.92      0.96    231084\n\n    accuracy                           0.96    470083\n   macro avg       0.96      0.96      0.96    470083\nweighted avg       0.96      0.96      0.96    470083\n"}}, "clients": {}, "accuracy": {"0": 0.5618411898612976, "1": 0.6179695725440979, "2": 0.6923586130142212, "3": 0.6745128035545349, "4": 0.7040905356407166, "5": 0.7143738269805908, "6": 0.9635170698165894, "7": 0.9613047242164612, "8": 0.8149582147598267, "9": 0.954420804977417, "10": 0.9479624032974243, "11": 0.9841049313545227, "12": 0.9462775588035583, "13": 0.9575372934341431, "14": 0.9778741002082825, "15": 0.9599921703338623, "16": 0.9459648728370667, "17": 0.9459627270698547, "18": 0.953750729560852, "19": 0.9484197497367859, "20": 0.9605473875999451}, "f1s": {"0": 0.5038884865874059, "1": 0.5960590426737953, "2": 0.658039167666551, "3": 0.6477414763064027, "4": 0.6780648012503911, "5": 0.6924524220234962, "6": 0.9634461610724007, "7": 0.9612215785084466, "8": 0.8116964387258963, "9": 0.9542909559258711, "10": 0.94777517339637, "11": 0.9840967051685835, "12": 0.9460731971171025, "13": 0.9574302444777203, "14": 0.977859631122121, "15": 0.9599009548946079, "16": 0.9457568833458788, "17": 0.9457547333799419, "18": 0.953615520759451, "19": 0.9482372359534533, "20": 0.9604594982543619}, "test_by_class": {"accuracy": {"Benign": {"0": 0.22364947133670016, "1": 0.3863907380365608, "2": 0.9999832635282992, "3": 0.3997715471612852, "4": 0.4203197502918422, "5": 0.44756254210268664, "6": 0.9999246858773467, "7": 0.9999246858773467, "8": 0.6799107946058351, "9": 0.9999372382311223, "10": 0.9999707111745237, "11": 0.9999372382311223, "12": 0.9999581588207482, "13": 0.9999414223490475, "14": 0.9964393156456721, "15": 0.9999832635282992, "16": 1.0, "17": 1.0, "18": 0.9999456064669726, "19": 0.9999414223490475, "20": 1.0}, "injection": {"0": 0.9934821750090025, "1": 1.0, "2": 0.2709398631616853, "3": 1.0, "4": 1.0, "5": 1.0, "6": 1.0, "7": 1.0, "8": 1.0, "9": 1.0, "10": 1.0, "11": 1.0, "12": 1.0, "13": 1.0, "14": 1.0, "15": 1.0, "16": 1.0, "17": 1.0, "18": 1.0, "19": 1.0, "20": 1.0}, "xss": {"0": 0.994122570445457, "1": 0.9993955175299917, "2": 0.1649958151213615, "3": 0.9999907002696922, "4": 1.0, "5": 1.0, "6": 1.0, "7": 1.0, "8": 1.0, "9": 1.0, "10": 1.0, "11": 1.0, "12": 1.0, "13": 1.0, "14": 1.0, "15": 1.0, "16": 1.0, "17": 1.0, "18": 1.0, "19": 1.0, "20": 1.0}, "password": {"0": 0.9920049381264513, "1": 1.0, "2": 0.2903794715028953, "3": 1.0, "4": 1.0, "5": 1.0, "6": 1.0, "7": 1.0, "8": 1.0, "9": 1.0, "10": 1.0, "11": 1.0, "12": 1.0, "13": 1.0, "14": 1.0, "15": 1.0, "16": 1.0, "17": 1.0, "18": 1.0, "19": 1.0, "20": 1.0}, "backdoor": {"0": 1.0, "1": 1.0, "2": 0.0007369196757553427, "3": 1.0, "4": 1.0, "5": 1.0, "6": 1.0, "7": 1.0, "8": 1.0, "9": 1.0, "10": 1.0, "11": 1.0, "12": 1.0, "13": 1.0, "14": 1.0, "15": 1.0, "16": 1.0, "17": 1.0, "18": 1.0, "19": 1.0, "20": 1.0}, "ransomware": {"0": 1.0, "1": 1.0, "2": 0.22745098039215686, "3": 1.0, "4": 1.0, "5": 1.0, "6": 1.0, "7": 1.0, "8": 1.0, "9": 1.0, "10": 1.0, "11": 1.0, "12": 1.0, "13": 1.0, "14": 1.0, "15": 1.0, "16": 1.0, "17": 1.0, "18": 1.0, "19": 1.0, "20": 1.0}, "scanning": {"0": 0.9806683236674951, "1": 1.0, "2": 0.16708091687379176, "3": 1.0, "4": 1.0, "5": 1.0, "6": 1.0, "7": 1.0, "8": 1.0, "9": 1.0, "10": 1.0, "11": 1.0, "12": 1.0, "13": 1.0, "14": 1.0, "15": 1.0, "16": 1.0, "17": 1.0, "18": 1.0, "19": 1.0, "20": 1.0}, "ddos": {"0": 0.1937144194026359, "1": 0.4426421274272791, "2": 0.9033767449114871, "3": 1.0, "4": 1.0, "5": 1.0, "6": 1.0, "7": 1.0, "8": 1.0, "9": 1.0, "10": 1.0, "11": 1.0, "12": 1.0, "13": 1.0, "14": 1.0, "15": 1.0, "16": 1.0, "17": 1.0, "18": 1.0, "19": 1.0, "20": 1.0}, "mitm": {"0": 0.8269230769230769, "1": 1.0, "2": 0.057692307692307696, "3": 1.0, "4": 1.0, "5": 1.0, "6": 1.0, "7": 1.0, "8": 1.0, "9": 1.0, "10": 1.0, "11": 1.0, "12": 1.0, "13": 1.0, "14": 1.0, "15": 1.0, "16": 1.0, "17": 1.0, "18": 1.0, "19": 1.0, "20": 1.0}, "dos": {"0": 1.0, "1": 1.0, "2": 0.0, "3": 1.0, "4": 1.0, "5": 1.0, "6": 1.0, "7": 1.0, "8": 1.0, "9": 1.0, "10": 1.0, "11": 1.0, "12": 1.0, "13": 1.0, "14": 1.0, "15": 1.0, "16": 1.0, "17": 1.0, "18": 1.0, "19": 1.0, "20": 1.0}, "DoS Hulk": {"0": 0.7069104960460101, "1": 0.6584291876347951, "2": 0.9106308411214953, "3": 0.6406362329259525, "4": 0.9917774982027319, "5": 0.9160226455787204, "6": 0.28518152408339326, "7": 0.25067397555715315, "8": 0.6229780733285406, "9": 0.11053199137311287, "10": 0.00013479511143062544, "11": 0.7199856218547808, "12": 0.0, "13": 0.21418943206326385, "14": 0.636861969805895, "15": 0.235127606038821, "16": 0.0, "17": 0.0, "18": 0.14481488138030194, "19": 0.0034597411933860534, "20": 0.2446531272465852}, "DoS GoldenEye": {"0": 0.08454810495626822, "1": 0.8182701652089407, "2": 0.20116618075801748, "3": 0.8299319727891157, "4": 0.8231292517006803, "5": 0.8338192419825073, "6": 0.001943634596695821, "7": 0.0, "8": 0.23517978620019436, "9": 0.0, "10": 0.0, "11": 0.0, "12": 0.0, "13": 0.0, "14": 0.0, "15": 0.0, "16": 0.0, "17": 0.0, "18": 0.0, "19": 0.0, "20": 0.0}, "PortScan": {"0": 0.9953400503778338, "1": 0.0028967254408060455, "2": 1.0, "3": 0.9500629722921914, "4": 1.0, "5": 1.0, "6": 1.0, "7": 1.0, "8": 1.0, "9": 1.0, "10": 1.0, "11": 1.0, "12": 1.0, "13": 1.0, "14": 1.0, "15": 1.0, "16": 1.0, "17": 1.0, "18": 1.0, "19": 1.0, "20": 1.0}, "DoS slowloris": {"0": 0.1733102253032929, "1": 0.6065857885615251, "2": 0.9948006932409013, "3": 0.9116117850953206, "4": 1.0, "5": 1.0, "6": 1.0, "7": 1.0, "8": 0.5909878682842288, "9": 0.8509532062391681, "10": 0.268630849220104, "11": 1.0, "12": 0.2720970537261698, "13": 0.24090121317157712, "14": 0.8613518197573656, "15": 0.9913344887348353, "16": 0.0, "17": 0.0, "18": 0.5753899480069324, "19": 0.5684575389948007, "20": 0.8682842287694974}, "FTP-Patator": {"0": 0.5031525851197982, "1": 0.0, "2": 1.0, "3": 0.9987389659520807, "4": 1.0, "5": 1.0, "6": 1.0, "7": 1.0, "8": 0.13619167717528374, "9": 1.0, "10": 0.9936948297604036, "11": 1.0, "12": 0.0, "13": 0.691046658259773, "14": 0.9949558638083228, "15": 1.0, "16": 0.0, "17": 0.0, "18": 0.14880201765447668, "19": 0.6519546027742749, "20": 1.0}, "SSH-Patator": {"0": 0.9949152542372881, "1": 0.005084745762711864, "2": 1.0, "3": 0.5186440677966102, "4": 1.0, "5": 1.0, "6": 1.0, "7": 1.0, "8": 1.0, "9": 1.0, "10": 1.0, "11": 1.0, "12": 1.0, "13": 1.0, "14": 1.0, "15": 1.0, "16": 1.0, "17": 1.0, "18": 1.0, "19": 1.0, "20": 1.0}, "Bot": {"0": 0.7142857142857143, "1": 0.01020408163265306, "2": 0.0, "3": 0.01020408163265306, "4": 0.01020408163265306, "5": 0.0, "6": 0.0, "7": 0.0, "8": 0.0, "9": 0.0, "10": 0.0, "11": 0.0, "12": 0.0, "13": 0.0, "14": 0.0, "15": 0.0, "16": 0.0, "17": 0.0, "18": 0.0, "19": 0.0, "20": 0.0}, "DoS Slowhttptest": {"0": 0.2018181818181818, "1": 0.74, "2": 0.9981818181818182, "3": 0.9127272727272727, "4": 1.0, "5": 1.0, "6": 1.0, "7": 0.509090909090909, "8": 0.6581818181818182, "9": 0.44727272727272727, "10": 0.0, "11": 1.0, "12": 0.0018181818181818182, "13": 0.0, "14": 0.7109090909090909, "15": 0.0, "16": 0.0, "17": 0.0, "18": 0.0018181818181818182, "19": 0.44727272727272727, "20": 0.2109090909090909}, "bruteforce": {"0": 0.9337748344370861, "1": 0.0, "2": 1.0, "3": 0.9602649006622517, "4": 1.0, "5": 1.0, "6": 1.0, "7": 1.0, "8": 1.0, "9": 1.0, "10": 1.0, "11": 1.0, "12": 1.0, "13": 1.0, "14": 1.0, "15": 1.0, "16": 1.0, "17": 1.0, "18": 1.0, "19": 1.0, "20": 1.0}, "Infiltration": {"0": 0.75, "1": 0.5, "2": 0.5, "3": 1.0, "4": 1.0, "5": 1.0, "6": 1.0, "7": 1.0, "8": 1.0, "9": 1.0, "10": 1.0, "11": 1.0, "12": 1.0, "13": 1.0, "14": 1.0, "15": 1.0, "16": 1.0, "17": 1.0, "18": 1.0, "19": 1.0, "20": 1.0}, "Web Attack \ufffd Sql Injection": {"0": 0.5, "1": 0.0, "2": 1.0, "3": 0.5, "4": 1.0, "5": 1.0, "6": 1.0, "7": 1.0, "8": 1.0, "9": 1.0, "10": 1.0, "11": 1.0, "12": 1.0, "13": 1.0, "14": 1.0, "15": 1.0, "16": 1.0, "17": 1.0, "18": 1.0, "19": 1.0, "20": 1.0}, "Heartbleed": {"0": 0.0, "1": 1.0, "2": 1.0, "3": 1.0, "4": 1.0, "5": 1.0, "6": 1.0, "7": 1.0, "8": 0.0, "9": 1.0, "10": 1.0, "11": 1.0, "12": 0.0, "13": 1.0, "14": 1.0, "15": 1.0, "16": 1.0, "17": 0.0, "18": 0.0, "19": 1.0, "20": 1.0}}, "f1s": {"Benign": {"0": 0.36554499728159595, "1": 0.5574052501011028, "2": 0.9999916316941216, "3": 0.5711954182409489, "4": 0.5918663740407418, "5": 0.6183671227808513, "6": 0.9999623415205657, "7": 0.9999623415205657, "8": 0.8094605937279731, "9": 0.9999686181307703, "10": 0.9999853553727999, "11": 0.9999686181307703, "12": 0.9999790789726939, "13": 0.9999707103166633, "14": 0.9982164825514988, "15": 0.9999916316941216, "16": 1.0, "17": 1.0, "18": 0.9999728024938022, "19": 0.9999707103166633, "20": 1.0}, "injection": {"0": 0.9967304322693692, "1": 1.0, "2": 0.42636142120473736, "3": 1.0, "4": 1.0, "5": 1.0, "6": 1.0, "7": 1.0, "8": 1.0, "9": 1.0, "10": 1.0, "11": 1.0, "12": 1.0, "13": 1.0, "14": 1.0, "15": 1.0, "16": 1.0, "17": 1.0, "18": 1.0, "19": 1.0, "20": 1.0}, "xss": {"0": 0.9970526237245136, "1": 0.9996976673876137, "2": 0.2832556357366371, "3": 0.9999953501132247, "4": 1.0, "5": 1.0, "6": 1.0, "7": 1.0, "8": 1.0, "9": 1.0, "10": 1.0, "11": 1.0, "12": 1.0, "13": 1.0, "14": 1.0, "15": 1.0, "16": 1.0, "17": 1.0, "18": 1.0, "19": 1.0, "20": 1.0}, "password": {"0": 0.9959864246716837, "1": 1.0, "2": 0.45006833712984057, "3": 1.0, "4": 1.0, "5": 1.0, "6": 1.0, "7": 1.0, "8": 1.0, "9": 1.0, "10": 1.0, "11": 1.0, "12": 1.0, "13": 1.0, "14": 1.0, "15": 1.0, "16": 1.0, "17": 1.0, "18": 1.0, "19": 1.0, "20": 1.0}, "backdoor": {"0": 1.0, "1": 1.0, "2": 0.0014727540500736377, "3": 1.0, "4": 1.0, "5": 1.0, "6": 1.0, "7": 1.0, "8": 1.0, "9": 1.0, "10": 1.0, "11": 1.0, "12": 1.0, "13": 1.0, "14": 1.0, "15": 1.0, "16": 1.0, "17": 1.0, "18": 1.0, "19": 1.0, "20": 1.0}, "ransomware": {"0": 1.0, "1": 1.0, "2": 0.3706070287539936, "3": 1.0, "4": 1.0, "5": 1.0, "6": 1.0, "7": 1.0, "8": 1.0, "9": 1.0, "10": 1.0, "11": 1.0, "12": 1.0, "13": 1.0, "14": 1.0, "15": 1.0, "16": 1.0, "17": 1.0, "18": 1.0, "19": 1.0, "20": 1.0}, "scanning": {"0": 0.990239821528165, "1": 1.0, "2": 0.2863227638428774, "3": 1.0, "4": 1.0, "5": 1.0, "6": 1.0, "7": 1.0, "8": 1.0, "9": 1.0, "10": 1.0, "11": 1.0, "12": 1.0, "13": 1.0, "14": 1.0, "15": 1.0, "16": 1.0, "17": 1.0, "18": 1.0, "19": 1.0, "20": 1.0}, "ddos": {"0": 0.3245573920428562, "1": 0.6136547921509271, "2": 0.9492358749539067, "3": 1.0, "4": 1.0, "5": 1.0, "6": 1.0, "7": 1.0, "8": 1.0, "9": 1.0, "10": 1.0, "11": 1.0, "12": 1.0, "13": 1.0, "14": 1.0, "15": 1.0, "16": 1.0, "17": 1.0, "18": 1.0, "19": 1.0, "20": 1.0}, "mitm": {"0": 0.9052631578947369, "1": 1.0, "2": 0.1090909090909091, "3": 1.0, "4": 1.0, "5": 1.0, "6": 1.0, "7": 1.0, "8": 1.0, "9": 1.0, "10": 1.0, "11": 1.0, "12": 1.0, "13": 1.0, "14": 1.0, "15": 1.0, "16": 1.0, "17": 1.0, "18": 1.0, "19": 1.0, "20": 1.0}, "dos": {"0": 1.0, "1": 1.0, "2": 0.0, "3": 1.0, "4": 1.0, "5": 1.0, "6": 1.0, "7": 1.0, "8": 1.0, "9": 1.0, "10": 1.0, "11": 1.0, "12": 1.0, "13": 1.0, "14": 1.0, "15": 1.0, "16": 1.0, "17": 1.0, "18": 1.0, "19": 1.0, "20": 1.0}, "DoS Hulk": {"0": 0.8282924004317038, "1": 0.7940395556759685, "2": 0.9532253133598287, "3": 0.7809607273922331, "4": 0.9958717769406031, "5": 0.9561710011021739, "6": 0.4437996014404083, "7": 0.400862223818933, "8": 0.7676974613105949, "9": 0.1990613367858877, "10": 0.00026955388831483896, "11": 0.8371995820271682, "12": 0.0, "13": 0.3528105687747474, "14": 0.7781498764754323, "15": 0.38073411182654876, "16": 0.0, "17": 0.0, "18": 0.2529926606224734, "19": 0.006895625307840416, "20": 0.39312660192772825}, "DoS GoldenEye": {"0": 0.15591397849462366, "1": 0.900053447354356, "2": 0.33495145631067963, "3": 0.9070631970260223, "4": 0.9029850746268657, "5": 0.9093799682034976, "6": 0.0038797284190106693, "7": 0.0, "8": 0.3808025177025964, "9": 0.0, "10": 0.0, "11": 0.0, "12": 0.0, "13": 0.0, "14": 0.0, "15": 0.0, "16": 0.0, "17": 0.0, "18": 0.0, "19": 0.0, "20": 0.0}, "PortScan": {"0": 0.9976645837278293, "1": 0.005776717317593872, "2": 1.0, "3": 0.9743920948106048, "4": 1.0, "5": 1.0, "6": 1.0, "7": 1.0, "8": 1.0, "9": 1.0, "10": 1.0, "11": 1.0, "12": 1.0, "13": 1.0, "14": 1.0, "15": 1.0, "16": 1.0, "17": 1.0, "18": 1.0, "19": 1.0, "20": 1.0}, "DoS slowloris": {"0": 0.29542097488921715, "1": 0.7551240560949298, "2": 0.9973935708079931, "3": 0.9537624660018131, "4": 1.0, "5": 1.0, "6": 1.0, "7": 1.0, "8": 0.7429193899782135, "9": 0.9194756554307116, "10": 0.42349726775956287, "11": 1.0, "12": 0.42779291553133514, "13": 0.388268156424581, "14": 0.9255121042830539, "15": 0.9956483899042646, "16": 0.0, "17": 0.0, "18": 0.7304730473047305, "19": 0.7248618784530386, "20": 0.9294990723562152}, "FTP-Patator": {"0": 0.6694630872483222, "1": 0.0, "2": 1.0, "3": 0.9993690851735015, "4": 1.0, "5": 1.0, "6": 1.0, "7": 1.0, "8": 0.2397336293007769, "9": 1.0, "10": 0.9968374446552815, "11": 1.0, "12": 0.0, "13": 0.8173005219985084, "14": 0.9974715549936789, "15": 1.0, "16": 0.0, "17": 0.0, "18": 0.25905598243688255, "19": 0.7893129770992366, "20": 1.0}, "SSH-Patator": {"0": 0.9974511469838573, "1": 0.01011804384485666, "2": 1.0, "3": 0.6830357142857143, "4": 1.0, "5": 1.0, "6": 1.0, "7": 1.0, "8": 1.0, "9": 1.0, "10": 1.0, "11": 1.0, "12": 1.0, "13": 1.0, "14": 1.0, "15": 1.0, "16": 1.0, "17": 1.0, "18": 1.0, "19": 1.0, "20": 1.0}, "Bot": {"0": 0.8333333333333334, "1": 0.020202020202020204, "2": 0.0, "3": 0.020202020202020204, "4": 0.020202020202020204, "5": 0.0, "6": 0.0, "7": 0.0, "8": 0.0, "9": 0.0, "10": 0.0, "11": 0.0, "12": 0.0, "13": 0.0, "14": 0.0, "15": 0.0, "16": 0.0, "17": 0.0, "18": 0.0, "19": 0.0, "20": 0.0}, "DoS Slowhttptest": {"0": 0.3358547655068079, "1": 0.8505747126436781, "2": 0.9990900818926298, "3": 0.9543726235741445, "4": 1.0, "5": 1.0, "6": 1.0, "7": 0.6746987951807228, "8": 0.793859649122807, "9": 0.6180904522613065, "10": 0.0, "11": 1.0, "12": 0.003629764065335753, "13": 0.0, "14": 0.8310308182784272, "15": 0.0, "16": 0.0, "17": 0.0, "18": 0.003629764065335753, "19": 0.6180904522613065, "20": 0.3483483483483483}, "bruteforce": {"0": 0.9657534246575342, "1": 0.0, "2": 1.0, "3": 0.9797297297297297, "4": 1.0, "5": 1.0, "6": 1.0, "7": 1.0, "8": 1.0, "9": 1.0, "10": 1.0, "11": 1.0, "12": 1.0, "13": 1.0, "14": 1.0, "15": 1.0, "16": 1.0, "17": 1.0, "18": 1.0, "19": 1.0, "20": 1.0}, "Infiltration": {"0": 0.8571428571428571, "1": 0.6666666666666666, "2": 0.6666666666666666, "3": 1.0, "4": 1.0, "5": 1.0, "6": 1.0, "7": 1.0, "8": 1.0, "9": 1.0, "10": 1.0, "11": 1.0, "12": 1.0, "13": 1.0, "14": 1.0, "15": 1.0, "16": 1.0, "17": 1.0, "18": 1.0, "19": 1.0, "20": 1.0}, "Web Attack \ufffd Sql Injection": {"0": 0.6666666666666666, "1": 0.0, "2": 1.0, "3": 0.6666666666666666, "4": 1.0, "5": 1.0, "6": 1.0, "7": 1.0, "8": 1.0, "9": 1.0, "10": 1.0, "11": 1.0, "12": 1.0, "13": 1.0, "14": 1.0, "15": 1.0, "16": 1.0, "17": 1.0, "18": 1.0, "19": 1.0, "20": 1.0}, "Heartbleed": {"0": 0.0, "1": 1.0, "2": 1.0, "3": 1.0, "4": 1.0, "5": 1.0, "6": 1.0, "7": 1.0, "8": 0.0, "9": 1.0, "10": 1.0, "11": 1.0, "12": 0.0, "13": 1.0, "14": 1.0, "15": 1.0, "16": 1.0, "17": 0.0, "18": 0.0, "19": 1.0, "20": 1.0}}, "length": 1}}}